visioncar/__init__.py
visioncar/__main__.py
visioncar/visioncar.py
visioncar-0.1.10.dist-info/LICENSE
visioncar-0.1.10.dist-info/METADATA
visioncar-0.1.10.dist-info/WHEEL
visioncar-0.1.10.dist-info/entry_points.txt
visioncar-0.1.10.dist-info/top_level.txt
visioncar-0.1.10.dist-info/RECORD
