Metadata-Version: 2.1
Name: visioncar
Version: 0.1.10
Summary: Python library for controlling ESP32 robot
Author: VisionCar team
Classifier: Development Status :: 5 - Production/Stable
Classifier: License :: OSI Approved :: MIT License
Classifier: Operating System :: OS Independent
Requires-Python: >=3.10
License-File: LICENSE
Requires-Dist: opencv-python ==4.8.*
Requires-Dist: requests ==2.*
Requires-Dist: zeroconf ==0.102.0
Requires-Dist: simplejpeg ==1.7.*
